setup.py
xml2obj.py
xml2obj.egg-info/PKG-INFO
xml2obj.egg-info/SOURCES.txt
xml2obj.egg-info/dependency_links.txt
xml2obj.egg-info/not-zip-safe
xml2obj.egg-info/top_level.txt