Metadata-Version: 1.1
Name: xml2obj
Version: 0.1
Summary: A simple function to converts XML data into native Python object
Home-page: UNKNOWN
Author: Lingchao Xin
Author-email: douglarek@gmail.com
License: UNKNOWN
Platform: UNKNOWN
Classifier: Development Status :: 4 - Beta
Classifier: Intended Audience :: Developers
Classifier: Natural Language :: English
Classifier: License :: OSI Approved :: Python Software Foundation License
Classifier: Programming Language :: Python
Classifier: Programming Language :: Python :: 2.6
Classifier: Programming Language :: Python :: 2.7
Classifier: Programming Language :: Python :: 3
Classifier: Programming Language :: Python :: 3.3
